<PAMDataset>
  <PAMRasterBand band="1">
    <Histograms>
      <HistItem>
        <HistMin>4.540630607150001</HistMin>
        <HistMax>5.133608692849999</HistMax>
        <BucketCount>1000</BucketCount>
        <IncludeOutOfRange>0</IncludeOutOfRange>
        <Approximate>0</Approximate>
        <HistCounts>1|0|0|0|0|0|0|0|0|0|0|0|0|0|0|0|0|0|0|0|0|0|0|0|0|0|0|0|0|0|0|0|0|0|0|0|0|0|0|0|0|0|0|0|0|0|0|0|0|0|0|1|0|0|1|0|0|0|0|0|0|0|0|0|0|0|0|0|0|0|0|0|1|0|0|0|0|1|0|0|0|0|0|0|0|0|0|2|0|1|0|0|0|0|0|0|0|0|0|0|0|0|0|0|0|0|1|0|0|0|0|1|0|0|1|1|1|0|1|0|1|0|0|0|0|0|0|0|0|0|0|0|0|2|1|0|2|0|0|0|0|1|1|0|0|0|3|0|1|0|0|2|1|2|2|0|1|0|2|1|2|0|1|1|2|0|1|0|1|1|0|2|0|2|2|4|1|1|1|0|1|0|2|3|2|3|1|0|3|0|1|1|4|4|1|2|0|2|3|5|1|0|1|2|1|3|2|5|1|5|1|4|2|5|0|2|1|7|7|1|1|5|4|2|2|2|2|3|3|7|2|4|7|6|2|4|7|6|6|4|5|6|3|11|7|7|9|3|3|3|6|8|7|9|4|9|6|7|9|7|10|6|6|5|5|10|9|7|12|8|9|6|9|7|9|5|10|15|8|16|6|8|16|14|6|11|16|9|12|13|6|15|10|9|14|13|18|13|11|13|24|8|15|22|21|20|18|15|16|19|27|16|25|20|18|30|28|19|26|32|33|25|17|30|32|19|30|30|40|30|35|30|26|35|33|32|27|59|46|43|33|35|45|40|32|45|50|52|50|44|50|59|51|46|56|57|71|77|54|71|66|83|80|56|72|60|73|81|93|87|77|80|86|77|81|94|93|93|95|81|95|77|84|97|88|114|102|124|123|125|125|121|119|130|122|150|151|137|146|145|151|162|162|175|163|181|183|184|219|224|247|249|274|304|323|369|385|446|481|556|620|716|822|923|1094|1300|1552|1846|2223|2735|3343|3858|3641|3796|4152|4686|5387|6053|4220|3951|3998|4197|4468|4897|5379|6062|6968|8343|11059|12769|10577|9221|8332|7815|7651|7824|8977|8739|7183|5998|5130|4436|3939|3483|3150|2810|2591|2431|2215|2087|1969|1862|1805|1721|1705|1753|1742|1586|1464|1311|1214|1109|1028|958|888|814|787|730|688|622|595|570|547|496|498|446|438|399|357|378|335|326|313|298|273|263|253|248|231|217|210|220|192|206|177|180|182|154|173|163|151|157|160|144|170|154|132|120|124|122|111|114|104|100|99|95|86|105|88|92|78|70|86|72|73|71|59|75|81|62|50|66|59|59|53|59|52|50|44|60|57|49|44|46|38|43|35|39|36|44|34|36|38|36|26|34|33|29|32|35|22|32|29|35|28|37|26|22|20|28|29|29|15|33|27|23|35|24|23|20|32|30|22|27|19|21|23|20|18|19|13|13|19|13|11|15|22|15|13|14|20|19|15|11|14|11|10|11|12|10|12|19|14|12|9|11|16|8|10|11|11|12|7|8|7|11|10|8|5|13|8|14|8|10|11|5|8|9|7|8|9|6|7|8|9|2|5|9|7|5|5|4|4|6|8|3|5|5|6|3|5|6|2|3|6|3|1|5|5|4|8|6|5|5|2|3|1|4|4|8|4|6|5|6|1|3|0|5|3|4|2|1|1|3|3|1|3|3|5|5|5|1|3|3|1|2|2|4|3|1|4|3|3|1|1|2|3|0|1|4|5|3|4|2|4|2|0|2|4|1|2|3|4|1|2|1|3|1|0|0|2|5|2|1|0|3|3|0|0|2|0|2|1|1|1|0|1|2|1|0|1|1|2|2|1|1|1|0|1|2|2|1|2|1|3|0|0|1|2|0|1|0|1|1|1|0|0|0|1|2|1|0|0|0|2|0|0|2|2|0|0|0|0|2|2|0|1|1|1|0|0|2|2|0|0|0|0|0|1|0|0|1|1|0|0|0|1|0|1|0|1|1|1|0|0|0|0|0|0|0|0|0|3|0|0|0|0|0|0|1|0|0|1|0|0|2|0|1|0|1|0|1|0|0|1|0|0|1|0|2|0|0|0|0|0|0|0|0|0|0|0|1|1|1|0|0|1|0|1|0|0|0|0|0|0|0|0|0|1|0|0|0|1|0|0|0|0|1|0|0|0|0|0|0|0|0|1|1|0|0|0|0|0|0|0|0|0|0|0|0|0|0|0|0|0|0|0|0|0|0|0|0|0|0|0|0|0|0|0|0|0|0|0|0|0|0|0|0|0|0|0|0|0|0|0|0|0|0|0|0|0|0|0|0|0|0|0|0|0|1</HistCounts>
      </HistItem>
    </Histograms>
    <Metadata>
      <MDI key="STATISTICS_MAXIMUM">5.1333125</MDI>
      <MDI key="STATISTICS_MEAN">4.8089202754112</MDI>
      <MDI key="STATISTICS_MINIMUM">4.5409268</MDI>
      <MDI key="STATISTICS_STDDEV">0.017991742863303</MDI>
    </Metadata>
  </PAMRasterBand>
</PAMDataset>
